[
  {
    "name": "Aboubakar Kamara",
    "position": "Forward",
    "team": "Fulham"
  },
  {
    "name": "Ainsley Maitland-Niles",
    "position": "Midfielder",
    "team": "Arsenal"
  },
  {
    "name": "Aleksandar Mitrovic",
    "position": "Forward",
    "team": "Fulham"
  },
  {
    "name": "Alexandre Lacazette",
    "position": "Forward",
    "team": "Arsenal"
  },
  {
    "name": "André-Frank Zambo Anguissa",
    "position": "Midfielder",
    "team": "Fulham"
  },
  {
    "name": "Bernd Leno",
    "position": "Goalkeeper",
    "team": "Arsenal"
  },
  {
    "name": "Bobby De Cordova-Reid",
    "position": "Forward",
    "team": "Fulham"
  },
  {
    "name": "Bruno Fernandes",
    "position": "Midfielder",
    "team": "Manchester United"
  },
  {
    "name": "Conor Gallagher",
    "position": "Midfielder",
    "team": "Crystal Palace"
  },
  {
    "name": "Dani Ceballos",
    "position": "Midfielder",
    "team": "Arsenal"
  },
  {
    "name": "Denis Odoi",
    "position": "Defender",
    "team": "Fulham"
  },
  {
    "name": "Eddie Nketiah",
    "position": "Forward",
    "team": "Arsenal"
  },
  {
    "name": "Ezri Konsa",
    "position": "Defender",
    "team": "Aston Villa"
  },
  {
    "name": "Gabriel Magalhães",
    "position": "Defender",
    "team": "Arsenal"
  },
  {
    "name": "Granit Xhaka",
    "position": "Midfielder",
    "team": "Arsenal"
  },
  {
    "name": "Harrison Reed",
    "position": "Midfielder",
    "team": "Fulham"
  },
  {
    "name": "Harry Kane",
    "position": "Forward",
    "team": "Tottenham Hotspur"
  },
  {
    "name": "Harry Maguire",
    "position": "Defender",
    "team": "Manchester United"
  },
  {
    "name": "Hector Bellerin",
    "position": "Defender",
    "team": "Arsenal"
  },
  {
    "name": "Ivan Cavaleiro",
    "position": "Forward",
    "team": "Fulham"
  },
  {
    "name": "Joe Bryan",
    "position": "Defender",
    "team": "Fulham"
  },
  {
    "name": "John McGinn",
    "position": "Midfielder",
    "team": "Aston Villa"
  },
  {
    "name": "Josh Onomah",
    "position": "Midfielder",
    "team": "Fulham"
  },
  {
    "name": "Kieran Tierney",
    "position": "Defender",
    "team": "Arsenal"
  },
  {
    "name": "Marek Rodák",
    "position": "Goalkeeper",
    "team": "Fulham"
  },
  {
    "name": "Michael Hector",
    "position": "Defender",
    "team": "Fulham"
  },
  {
    "name": "Michail Antonio",
    "position": "Forward",
    "team": "West Ham United"
  },
  {
    "name": "Mohamed Elneny",
    "position": "Midfielder",
    "team": "Arsenal"
  },
  {
    "name": "Mohamed Salah",
    "position": "Forward",
    "team": "Liverpool"
  },
  {
    "name": "Neeskens Kebano",
    "position": "Midfielder",
    "team": "Fulham"
  },
  {
    "name": "Nicolas Pépé",
    "position": "Forward",
    "team": "Arsenal"
  },
  {
    "name": "Pierre-Emerick Aubameyang",
    "position": "Forward",
    "team": "Arsenal"
  },
  {
    "name": "Raúl Jiménez",
    "position": "Forward",
    "team": "Wolverhampton Wanderers"
  },
  {
    "name": "Rob Holding",
    "position": "Defender",
    "team": "Arsenal"
  },
  {
    "name": "Tim Ream",
    "position": "Defender",
    "team": "Fulham"
  },
  {
    "name": "Tom Cairney",
    "position": "Midfielder",
    "team": "Fulham"
  },
  {
    "name": "Willian",
    "position": "Forward",
    "team": "Arsenal"
  }
]